README.rst
setup.py
hyperswitch/__init__.py
hyperswitch/controllers.py
hyperswitch/filters.py
hyperswitch/windows.py
hyperswitch.egg-info/PKG-INFO
hyperswitch.egg-info/SOURCES.txt
hyperswitch.egg-info/dependency_links.txt
hyperswitch.egg-info/entry_points.txt
hyperswitch.egg-info/not-zip-safe
hyperswitch.egg-info/requires.txt
hyperswitch.egg-info/top_level.txt