Metadata-Version: 1.0
Name: hyperswitch
Version: 0.1
Summary: A context switching application for Linux
Home-page: https://bitbucket.org/TheNoctambulist/hyperswitch/
Author: TheNoctambulist
Author-email: UNKNOWN
License: MIT License
Platform: UNKNOWN
